community_solar_programs/__init__.py
community_solar_programs/massachusetts_smart.py
community_solar_programs-0.1.0.dist-info/METADATA
community_solar_programs-0.1.0.dist-info/WHEEL
community_solar_programs-0.1.0.dist-info/RECORD
