Metadata-Version: 2.1
Name: community-solar-programs
Version: 0.1.0
Summary: Community solar regulation as code. A static library of functions that calculate compensation for various community solar programs.
Author: lyon lay
Author-email: lay.lyon@gmail.com
Requires-Python: >=3.11,<4.0
Classifier: Programming Language :: Python :: 3
Classifier: Programming Language :: Python :: 3.11
Classifier: Programming Language :: Python :: 3.12
